<?xml version="1.0" encoding="UTF-8"?>
<data>
	<key id="add">Add</key>
	<key id="click">Click</key>
	<key id="clicks">Clicks</key>
	<key id="continue">Continue</key>
	<key id="continue_as_guest">Continue as guest</key>
	<key id="count_long">Count</key>
	<key id="count_short">Count</key>
	<key id="country">Country</key>
	<key id="day">Day</key>
	<key id="email">Email</key>
	<key id="login">Login</key>
	<key id="month">Month</key>
	<key id="no">No</key>
	<key id="password">Password</key>
	<key id="registration">Registration</key>
	<key id="start">Start</key>
	<key id="to_save">to save</key>
	<key id="total">Total</key>
	<key id="warning_lose_progress">Are you sure? Current progress will be lost.</key>
	<key id="week">Week</key>
	<key id="world">world</key>
	<key id="yes">Yes</key>
</data>